vvapp/__init__.py
vvapp/_nbdev.py
vvapp/app_templates.py
vvapp/inputs.py
vvapp/outputs.py
vvapp-0.0.15.dist-info/LICENSE
vvapp-0.0.15.dist-info/METADATA
vvapp-0.0.15.dist-info/WHEEL
vvapp-0.0.15.dist-info/entry_points.txt
vvapp-0.0.15.dist-info/top_level.txt
vvapp-0.0.15.dist-info/RECORD
