Metadata-Version: 2.1
Name: vvapp
Version: 0.0.15
Summary: A python library simplifying development of ipyvuetify voila apps
Home-page: https://github.com/radinplaid/vvapp/tree/master/
Author: Mark Franey
Author-email: franey.mark@gmail.com
License: Apache Software License 2.0
Keywords: python,jupyter,voila
Platform: UNKNOWN
Classifier: Development Status :: 3 - Alpha
Classifier: Intended Audience :: Developers
Classifier: License :: OSI Approved :: Apache Software License
Classifier: Natural Language :: English
Classifier: Programming Language :: Python :: 3.6
Classifier: Programming Language :: Python :: 3.7
Classifier: Programming Language :: Python :: 3.8
Requires-Python: >=3.6
Requires-Dist: ipyvuetify
Requires-Dist: traitlets
Requires-Dist: pandas
Requires-Dist: numpy
Requires-Dist: markdown
Requires-Dist: ipywidgets
Requires-Dist: nbdev
